zither/__init__.py
zither/__main__.py
zither/zither.py
zither-0.2.dist-info/DESCRIPTION.rst
zither-0.2.dist-info/entry_points.txt
zither-0.2.dist-info/METADATA
zither-0.2.dist-info/metadata.json
zither-0.2.dist-info/RECORD
zither-0.2.dist-info/top_level.txt
zither-0.2.dist-info/WHEEL
