Metadata-Version: 2.0
Name: zither
Version: 0.2
Summary: Command-line tool to pull raw depths and alt freqs from BAM file(s) based on an existing VCF, writing output as new VCF to stdout.
Home-page: https://github.com/umich-brcf-bioinf/Zither
Author: University of Michigan Bioinformatics Core
Author-email: bfx-zither@umich.edu
License: Apache
Keywords: VCF bioinformatic exome-seq DNA-seq variant-call-format BAM
Platform: UNKNOWN
Classifier: Development Status :: 4 - Beta
Classifier: Environment :: Console
Classifier: Intended Audience :: Science/Research
Classifier: License :: OSI Approved :: Apache Software License
Classifier: Operating System :: Unix
Classifier: Programming Language :: Python :: 2.7
Classifier: Programming Language :: Python :: 3
Classifier: Topic :: Scientific/Engineering :: Bio-Informatics
Requires-Dist: pysam
